odoo9_addon_purchase_batch_invoicing-9.0.1.0.0-py2.7-nspkg.pth
odoo9_addon_purchase_batch_invoicing-9.0.1.0.0.dist-info/top_level.txt
odoo9_addon_purchase_batch_invoicing-9.0.1.0.0.dist-info/WHEEL
odoo9_addon_purchase_batch_invoicing-9.0.1.0.0.dist-info/RECORD
odoo9_addon_purchase_batch_invoicing-9.0.1.0.0.dist-info/metadata.json
odoo9_addon_purchase_batch_invoicing-9.0.1.0.0.dist-info/DESCRIPTION.rst
odoo9_addon_purchase_batch_invoicing-9.0.1.0.0.dist-info/METADATA
odoo9_addon_purchase_batch_invoicing-9.0.1.0.0.dist-info/namespace_packages.txt
odoo_addons/purchase_batch_invoicing/__openerp__.py
odoo_addons/purchase_batch_invoicing/__init__.py
odoo_addons/purchase_batch_invoicing/README.rst
odoo_addons/purchase_batch_invoicing/i18n/es.po
odoo_addons/purchase_batch_invoicing/views/purchase_order_view.xml
odoo_addons/purchase_batch_invoicing/wizards/purchase_batch_invoicing.py
odoo_addons/purchase_batch_invoicing/wizards/purchase_batch_invoicing_view.xml
odoo_addons/purchase_batch_invoicing/wizards/__init__.py
odoo_addons/purchase_batch_invoicing/data/ir_cron_data.xml
odoo_addons/purchase_batch_invoicing/tests/__init__.py
odoo_addons/purchase_batch_invoicing/tests/test_invoicing.py
odoo_addons/purchase_batch_invoicing/static/description/wizard.png
odoo_addons/purchase_batch_invoicing/static/description/icon.png
